maleo_core/__init__.py
maleo_core/clients/__init__.py
maleo_core/clients/general/__init__.py
maleo_core/clients/general/http.py
maleo_core/clients/google/__init__.py
maleo_core/clients/google/cloud/__init__.py
maleo_core/clients/google/cloud/logging.py
maleo_core/clients/google/cloud/secret.py
maleo_core/clients/google/cloud/storage.py
maleo_core/clients/maleo_suite/__init__.py
maleo_core/clients/maleo_suite/maleo_access/__init__.py
maleo_core/clients/maleo_suite/maleo_access/http/__init__.py
maleo_core/clients/maleo_suite/maleo_access/http/manager.py
maleo_core/clients/maleo_suite/maleo_access/http/controllers/__init__.py
maleo_core/clients/maleo_suite/maleo_access/http/controllers/blood_type.py
maleo_core/clients/maleo_suite/maleo_access/http/controllers/gender.py
maleo_core/clients/maleo_suite/maleo_access/http/controllers/organization.py
maleo_core/clients/maleo_suite/maleo_access/http/controllers/organization_role.py
maleo_core/clients/maleo_suite/maleo_access/http/controllers/organization_type.py
maleo_core/clients/maleo_suite/maleo_access/http/controllers/system_role.py
maleo_core/clients/maleo_suite/maleo_access/http/controllers/user.py
maleo_core/clients/maleo_suite/maleo_access/http/controllers/user_profile.py
maleo_core/clients/maleo_suite/maleo_access/http/controllers/user_type.py
maleo_core/clients/maleo_suite/maleo_access/http/services/__init__.py
maleo_core/clients/maleo_suite/maleo_access/http/services/blood_type.py
maleo_core/clients/maleo_suite/maleo_access/http/services/gender.py
maleo_core/clients/maleo_suite/maleo_access/http/services/organization.py
maleo_core/clients/maleo_suite/maleo_access/http/services/organization_role.py
maleo_core/clients/maleo_suite/maleo_access/http/services/organization_type.py
maleo_core/clients/maleo_suite/maleo_access/http/services/system_role.py
maleo_core/clients/maleo_suite/maleo_access/http/services/user.py
maleo_core/clients/maleo_suite/maleo_access/http/services/user_profile.py
maleo_core-0.4.10.dist-info/METADATA
maleo_core-0.4.10.dist-info/WHEEL
maleo_core-0.4.10.dist-info/top_level.txt
maleo_core-0.4.10.dist-info/RECORD
