Metadata-Version: 2.4
Name: maleo_core
Version: 0.4.10
Summary: Core package for Maleo
Author-email: Agra Bima Yuda <agra@nexmedis.com>
License: MIT
Requires-Python: >=3.7
Requires-Dist: annotated-types>=0.7.0
Requires-Dist: anyio>=4.8.0
Requires-Dist: build>=1.2.2.post1
Requires-Dist: cachetools>=5.5.2
Requires-Dist: certifi>=2025.1.31
Requires-Dist: cffi>=1.17.1
Requires-Dist: charset-normalizer>=3.4.1
Requires-Dist: cryptography>=44.0.1
Requires-Dist: Deprecated>=1.2.18
Requires-Dist: docutils>=0.21.2
Requires-Dist: fastapi>=0.115.8
Requires-Dist: google-api-core>=2.24.1
Requires-Dist: google-auth>=2.38.0
Requires-Dist: google-cloud-appengine-logging>=1.6.1
Requires-Dist: google-cloud-audit-log>=0.3.2
Requires-Dist: google-cloud-core>=2.4.3
Requires-Dist: google-cloud-logging>=3.11.4
Requires-Dist: google-cloud-secret-manager>=2.23.1
Requires-Dist: google-cloud-storage>=3.1.0
Requires-Dist: google-crc32c>=1.7.1
Requires-Dist: google-resumable-media>=2.7.2
Requires-Dist: googleapis-common-protos>=1.68.0
Requires-Dist: greenlet>=3.1.1
Requires-Dist: grpc-google-iam-v1>=0.14.0
Requires-Dist: grpcio>=1.70.0
Requires-Dist: grpcio-status>=1.70.0
Requires-Dist: h11>=0.14.0
Requires-Dist: httpcore>=1.0.7
Requires-Dist: httpx>=0.28.1
Requires-Dist: id>=1.5.0
Requires-Dist: idna>=3.10
Requires-Dist: importlib_metadata>=8.6.1
Requires-Dist: jaraco.classes>=3.4.0
Requires-Dist: jaraco.context>=6.0.1
Requires-Dist: jaraco.functools>=4.1.0
Requires-Dist: jeepney>=0.8.0
Requires-Dist: keyring>=25.6.0
Requires-Dist: markdown-it-py>=3.0.0
Requires-Dist: mdurl>=0.1.2
Requires-Dist: more-itertools>=10.6.0
Requires-Dist: nh3>=0.2.20
Requires-Dist: opentelemetry-api>=1.31.1
Requires-Dist: packaging>=24.2
Requires-Dist: passlib>=1.7.4
Requires-Dist: proto-plus>=1.26.0
Requires-Dist: protobuf>=5.29.3
Requires-Dist: pyasn1>=0.6.1
Requires-Dist: pyasn1_modules>=0.4.1
Requires-Dist: pycparser>=2.22
Requires-Dist: pycryptodome>=3.21.0
Requires-Dist: pydantic>=2.10.6
Requires-Dist: pydantic_core>=2.27.2
Requires-Dist: Pygments>=2.19.1
Requires-Dist: PyJWT>=2.10.1
Requires-Dist: pyproject_hooks>=1.2.0
Requires-Dist: readme_renderer>=44.0
Requires-Dist: requests>=2.32.3
Requires-Dist: requests-toolbelt>=1.0.0
Requires-Dist: rfc3986>=2.0.0
Requires-Dist: rich>=13.9.4
Requires-Dist: rsa>=4.9
Requires-Dist: SecretStorage>=3.3.3
Requires-Dist: setuptools>=75.8.0
Requires-Dist: sniffio>=1.3.1
Requires-Dist: SQLAlchemy>=2.0.38
Requires-Dist: starlette>=0.45.3
Requires-Dist: twine>=6.1.0
Requires-Dist: typing_extensions>=4.12.2
Requires-Dist: urllib3>=2.3.0
Requires-Dist: wrapt>=1.17.2
Requires-Dist: zipp>=3.21.0
